pysinger/__init__.py
pysinger/singer.py
pysinger/tap.py
pysinger/target.py
pysinger-0.0.3.dist-info/LICENSE
pysinger-0.0.3.dist-info/METADATA
pysinger-0.0.3.dist-info/WHEEL
pysinger-0.0.3.dist-info/top_level.txt
pysinger-0.0.3.dist-info/RECORD
