Metadata-Version: 2.1
Name: pysinger
Version: 0.0.3
Summary: Singer python wrapper for easy execution
Home-page: https://github.com/izzudinhafiz/pysinger
Author: Izzudin Hafiz
Author-email: izzudin.hafiz@gmail.com
License: MIT
Platform: UNKNOWN
Classifier: Programming Language :: Python :: 3.7
Classifier: Intended Audience :: Developers
Classifier: License :: OSI Approved :: MIT License
Classifier: Operating System :: POSIX :: Linux
Requires-Python: >=3.7
License-File: LICENSE
